frisco_mazi.py
frisco_mazi-0.2.1.dist-info/entry_points.txt
frisco_mazi-0.2.1.dist-info/WHEEL
frisco_mazi-0.2.1.dist-info/METADATA
frisco_mazi-0.2.1.dist-info/RECORD
